setup.py
gauss_bino_distributions_ercelik/Binomialdistribution_challenge.py
gauss_bino_distributions_ercelik/Gaussiandistribution.py
gauss_bino_distributions_ercelik/Generaldistribution.py
gauss_bino_distributions_ercelik/__init__.py
gauss_bino_distributions_ercelik.egg-info/PKG-INFO
gauss_bino_distributions_ercelik.egg-info/SOURCES.txt
gauss_bino_distributions_ercelik.egg-info/dependency_links.txt
gauss_bino_distributions_ercelik.egg-info/not-zip-safe
gauss_bino_distributions_ercelik.egg-info/top_level.txt