Metadata-Version: 1.0
Name: gauss-bino-distributions-ercelik
Version: 0.1
Summary: Gaussian and Binomial distributions
Home-page: UNKNOWN
Author: Dilay Fidan Ercelik
Author-email: dilay.ercelik@gmail.com
License: UNKNOWN
Platform: UNKNOWN
